raspberry_i2c_tb6612fng/__init__.py
raspberry_i2c_tb6612fng/codes.py
raspberry_i2c_tb6612fng/motors.py
raspberry_i2c_tb6612fng/stepper.py
raspberry_i2c_tb6612fng/easings/__init__.py
raspberry_i2c_tb6612fng-0.3.0.dist-info/licenses/LICENSE.txt
raspberry_i2c_tb6612fng-0.3.0.dist-info/METADATA
raspberry_i2c_tb6612fng-0.3.0.dist-info/WHEEL
raspberry_i2c_tb6612fng-0.3.0.dist-info/top_level.txt
raspberry_i2c_tb6612fng-0.3.0.dist-info/RECORD
