Metadata-Version: 2.4
Name: raspberry-i2c-tb6612fng
Version: 0.3.0
Summary: A port of Grove Motor Driver TB6612FNG library for python and RaspberryPI. This library also includes easing functions to control your motors with smooth transitions.
Home-page: https://github.com/MarkusBansky/raspberry-i2c-tb6612fng
Author: Markiian Benovskyi
Author-email: admin@markiian-benovskyi.com
License: GNU General Public License
Keywords: raspberry i2c tb6612fng grove motor
Classifier: Programming Language :: Python :: 3.13
Classifier: License :: OSI Approved :: GNU General Public License v3 or later (GPLv3+)
Classifier: Operating System :: POSIX :: Linux
Requires-Python: >=3.13
License-File: LICENSE.txt
Requires-Dist: smbus
Dynamic: author
Dynamic: author-email
Dynamic: classifier
Dynamic: description
Dynamic: description-content-type
Dynamic: home-page
Dynamic: keywords
Dynamic: license
Dynamic: license-file
Dynamic: requires-dist
Dynamic: requires-python
Dynamic: summary
